radiocc/__init__.py
radiocc/assets/information/PATH_S.txt
radiocc/assets/information/PATH_X.txt
radiocc/assets/information/PLANETS_SATELLITE.txt
radiocc/assets/information/SPACECRAFT.txt
radiocc/assets/information/STATION.txt
radiocc/assets/interface/icon.ico
radiocc/assets/interface/icon.png
radiocc/assets/interface/interface.glade
radiocc/cli.py
radiocc/config.py
radiocc/constants.py
radiocc/core.py
radiocc/download_data.py
radiocc/export.py
radiocc/interface.py
radiocc/model.py
radiocc/old/R10_Avg_BendAng_ImpParam.py
radiocc/old/R11_Refractivity_and_Bending_Radius_v2.py
radiocc/old/R12_Electron_Density.py
radiocc/old/R13_Neutral_Number_Density.py
radiocc/old/R13a_Pressure_and_Temperature.py
radiocc/old/R14_Plot_check.py
radiocc/old/R15_Errors.py
radiocc/old/R16_Biasfit_Correction.py
radiocc/old/R17_Plot_profiles.py
radiocc/old/R17_Run_Routines1.py
radiocc/old/R18_Occ_Info_MEX.py
radiocc/old/R18_Occ_Info_MVN.py
radiocc/old/R4_State_Vectors_twoway_v2.py
radiocc/old/R5_Foot_Print.py
radiocc/old/R6_Framework_Conversion.py
radiocc/old/R7_Offset_Correction.py
radiocc/old/R8_Plot_Doppler_1.py
radiocc/old/R9_BendAng_ImpParam_dn.py
radiocc/old/R9_BendAng_ImpParam_up.py
radiocc/old/__init__.py
radiocc/process_descriptor.py
radiocc/process_parser.py
radiocc/reconstruct.py
radiocc/utils.py
radiocc-0.6.24.dist-info/LICENSE
radiocc-0.6.24.dist-info/METADATA
radiocc-0.6.24.dist-info/WHEEL
radiocc-0.6.24.dist-info/entry_points.txt
radiocc-0.6.24.dist-info/RECORD
