Metadata-Version: 2.1
Name: radiocc
Version: 0.6.24
Summary: Radio occultations
Home-page: https://gitlab-as.oma.be/radiocc/radiocc
License: Apache-2.0
Keywords: radio,occultation
Author: Ananya Krishnan
Author-email: ananyakrishnaniiserk@gmail.com
Requires-Python: >=3.9,<3.11
Classifier: Development Status :: 4 - Beta
Classifier: Environment :: Console
Classifier: Framework :: Matplotlib
Classifier: Framework :: Pytest
Classifier: Intended Audience :: Science/Research
Classifier: Intended Audience :: Telecommunications Industry
Classifier: License :: OSI Approved :: Apache Software License
Classifier: Natural Language :: English
Classifier: Operating System :: Microsoft :: Windows :: Windows 10
Classifier: Operating System :: POSIX :: Linux
Classifier: Programming Language :: Python :: 3
Classifier: Programming Language :: Python :: 3.9
Classifier: Programming Language :: Python :: 3.10
Classifier: Topic :: Scientific/Engineering :: Astronomy
Classifier: Topic :: Scientific/Engineering :: Atmospheric Science
Classifier: Topic :: Scientific/Engineering :: Mathematics
Classifier: Topic :: Scientific/Engineering :: Physics
Classifier: Topic :: Scientific/Engineering :: Visualization
Classifier: Topic :: Software Development :: Libraries :: Python Modules
Provides-Extra: doc
Provides-Extra: test
Requires-Dist: PyGObject
Requires-Dist: PyYAML
Requires-Dist: arrow
Requires-Dist: bs4
Requires-Dist: click
Requires-Dist: colored
Requires-Dist: dotmap
Requires-Dist: envtoml
Requires-Dist: matplotlib
Requires-Dist: nptyping
Requires-Dist: numpy
Requires-Dist: pandas
Requires-Dist: pudb
Requires-Dist: pycairo
Requires-Dist: requests
Requires-Dist: ruamel.yaml
Requires-Dist: scipy
Requires-Dist: spiceypy
Requires-Dist: tqdm
Requires-Dist: urlpath
Project-URL: Repository, https://gitlab-as.oma.be/radiocc/radiocc
